eda_toolkit/__init__.py
eda_toolkit/_plot_utils.py
eda_toolkit/art.py
eda_toolkit/data_manager.py
eda_toolkit/plots.py
eda_toolkit-0.0.22.dist-info/licenses/LICENSE.md
eda_toolkit-0.0.22.dist-info/METADATA
eda_toolkit-0.0.22.dist-info/WHEEL
eda_toolkit-0.0.22.dist-info/top_level.txt
eda_toolkit-0.0.22.dist-info/RECORD
