Metadata-Version: 2.4
Name: eda_toolkit
Version: 0.0.22
Summary: A Python library for EDA, including visualizations, directory management, data preprocessing, reporting, and more.
Author: Leonid Shpaner, Oscar Gil
Author-email: "Leonid Shpaner, Oscar Gil" <lshpaner@ucla.edu>
Project-URL: Documentation, https://lshpaner.github.io/eda_toolkit/
Project-URL: Source Code, https://github.com/lshpaner/eda_toolkit/
Project-URL: Leonid Shpaner's Website, https://www.leonshpaner.com
Project-URL: Oscar Gil's Website, https://www.oscargildata.com
Project-URL: Zenodo Archive, https://zenodo.org/records/13162633
Classifier: Programming Language :: Python :: 3
Classifier: License :: OSI Approved :: MIT License
Classifier: Operating System :: OS Independent
Requires-Python: >=3.7.4
License-File: LICENSE.md
Requires-Dist: jinja2==3.1.4
Requires-Dist: matplotlib<=3.9.2,>=3.5.3
Requires-Dist: nbformat<=5.10.4,>=4.2.0
Requires-Dist: numpy<=2.1.2,>=1.21.6
Requires-Dist: pandas<=2.2.3,>=1.3.5
Requires-Dist: plotly<=5.24.1,>=5.18.0
Requires-Dist: scikit-learn<=1.5.2,>=1.0.2
Requires-Dist: scipy<=1.16.3,>=1.5.4
Requires-Dist: seaborn<=0.13.2,>=0.12.2
Requires-Dist: tqdm<=4.67.1,>=4.66.4
Requires-Dist: xlsxwriter==3.2.0
Dynamic: author
Dynamic: license-file
Dynamic: requires-python
